{"cod":"200","message":0.0023,"cnt":40,"list":[{"dt":1534615200,"main":{"temp":294.8,"temp_min":294.8,"temp_max":295.414,"pressure":1028.84,"sea_level":1033.17,"grnd_level":1028.84,"humidity":46,"temp_kf":-0.62},"weather":[{"id":800,"main":"Clear","description":"clear sky","icon":"01d"}],"clouds":{"all":0},"wind":{"speed":4.66,"deg":257.003},"sys":{"pod":"d"},"dt_txt":"2018-08-18 18:00:00"},{"dt":1534626000,"main":{"temp":290.57,"temp_min":290.57,"temp_max":291.027,"pressure":1029.34,"sea_level":1033.82,"grnd_level":1029.34,"humidity":72,"temp_kf":-0.46},"weather":[{"id":800,"main":"Clear","description":"clear sky","icon":"01n"}],"clouds":{"all":0},"wind":{"speed":3.16,"deg":251.001},"sys":{"pod":"n"},"dt_txt":"2018-08-18 21:00:00"},{"dt":1534636800,"main":{"temp":288.48,"temp_min":288.48,"temp_max":288.791,"pressure":1029.77,"sea_level":1034.21,"grnd_level":1029.77,"humidity":90,"temp_kf":-0.31},"weather":[{"id":800,"main":"Clear","description":"clear sky","icon":"01n"}],"clouds":{"all":0},"wind":{"speed":3.32,"deg":246.502},"sys":{"pod":"n"},"dt_txt":"2018-08-19 00:00:00"},{"dt":1534647600,"main":{"temp":286.78,"temp_min":286.78,"temp_max":286.937,"pressure":1029.79,"sea_level":1034.21,"grnd_level":1029.79,"humidity":95,"temp_kf":-0.15},"weather":[{"id":800,"main":"Clear","description":"clear sky","icon":"02n"}],"clouds":{"all":8},"wind":{"speed":2.07,"deg":237.503},"sys":{"pod":"n"},"dt_txt":"2018-08-19 03:00:00"},{"dt":1534658400,"main":{"temp":289.466,"temp_min":289.466,"temp_max":289.466,"pressure":1029.97,"sea_level":1034.4,"grnd_level":1029.97,"humidity":83,"temp_kf":0},"weather":[{"id":801,"main":"Clouds","description":"few clouds","icon":"02d"}],"clouds":{"all":24},"wind":{"speed":4,"deg":239.006},"sys":{"pod":"d"},"dt_txt":"2018-08-19 06:00:00"},{"dt":1534669200,"main":{"temp":295.086,"temp_min":295.086,"temp_max":295.086,"pressure":1029.85,"sea_level":1034.2,"grnd_level":1029.85,"humidity":64,"temp_kf":0},"weather":[{"id":802,"main":"Clouds","description":"scattered clouds","icon":"03d"}],"clouds":{"all":44},"wind":{"speed":3.9,"deg":244.001},"sys":{"pod":"d"},"dt_txt":"2018-08-19 09:00:00"},{"dt":1534680000,"main":{"temp":297.517,"temp_min":297.517,"temp_max":297.517,"pressure":1028.34,"sea_level":1032.69,"grnd_level":1028.34,"humidity":57,"temp_kf":0},"weather":[{"id":803,"main":"Clouds","description":"broken clouds","icon":"04d"}],"clouds":{"all":56},"wind":{"speed":4.31,"deg":245.001},"sys":{"pod":"d"},"dt_txt":"2018-08-19 12:00:00"},{"dt":1534690800,"main":{"temp":298.859,"temp_min":298.859,"temp_max":298.859,"pressure":1026.49,"sea_level":1030.85,"grnd_level":1026.49,"humidity":52,"temp_kf":0},"weather":[{"id":803,"main":"Clouds","description":"broken clouds","icon":"04d"}],"clouds":{"all":56},"wind":{"speed":4.41,"deg":244.002},"sys":{"pod":"d"},"dt_txt":"2018-08-19 15:00:00"},{"dt":1534701600,"main":{"temp":297.955,"temp_min":297.955,"temp_max":297.955,"pressure":1024.91,"sea_level":1029.29,"grnd_level":1024.91,"humidity":47,"temp_kf":0},"weather":[{"id":803,"main":"Clouds","description":"broken clouds","icon":"04d"}],"clouds":{"all":64},"wind":{"speed":4.66,"deg":243.002},"sys":{"pod":"d"},"dt_txt":"2018-08-19 18:00:00"},{"dt":1534712400,"main":{"temp":294.672,"temp_min":294.672,"temp_max":294.672,"pressure":1024.92,"sea_level":1029.23,"grnd_level":1024.92,"humidity":60,"temp_kf":0},"weather":[{"id":802,"main":"Clouds","description":"scattered clouds","icon":"03n"}],"clouds":{"all":32},"wind":{"speed":4.92,"deg":256.5},"sys":{"pod":"n"},"dt_txt":"2018-08-19 21:00:00"},{"dt":1534723200,"main":{"temp":293.528,"temp_min":293.528,"temp_max":293.528,"pressure":1024.28,"sea_level":1028.62,"grnd_level":1024.28,"humidity":76,"temp_kf":0},"weather":[{"id":801,"main":"Clouds","description":"few clouds","icon":"02n"}],"clouds":{"all":24},"wind":{"speed":4.52,"deg":245.501},"sys":{"pod":"n"},"dt_txt":"2018-08-20 00:00:00"},{"dt":1534734000,"main":{"temp":291.653,"temp_min":291.653,"temp_max":291.653,"pressure":1023.74,"sea_level":1028.09,"grnd_level":1023.74,"humidity":77,"temp_kf":0},"weather":[{"id":500,"main":"Rain","description":"light rain","icon":"10n"}],"clouds":{"all":48},"wind":{"speed":5.2,"deg":250.503},"rain":{"3h":0.03},"sys":{"pod":"n"},"dt_txt":"2018-08-20 03:00:00"},{"dt":1534744800,"main":{"temp":292.731,"temp_min":292.731,"temp_max":292.731,"pressure":1023.65,"sea_level":1028.02,"grnd_level":1023.65,"humidity":86,"temp_kf":0},"weather":[{"id":500,"main":"Rain","description":"light rain","icon":"10d"}],"clouds":{"all":80},"wind":{"speed":5.52,"deg":256.002},"rain":{"3h":0.17},"sys":{"pod":"d"},"dt_txt":"2018-08-20 06:00:00"},{"dt":1534755600,"main":{"temp":294.294,"temp_min":294.294,"temp_max":294.294,"pressure":1024.48,"sea_level":1028.86,"grnd_level":1024.48,"humidity":75,"temp_kf":0},"weather":[{"id":500,"main":"Rain","description":"light rain","icon":"10d"}],"clouds":{"all":64},"wind":{"speed":6.16,"deg":270.502},"rain":{"3h":0.14},"sys":{"pod":"d"},"dt_txt":"2018-08-20 09:00:00"},{"dt":1534766400,"main":{"temp":295.266,"temp_min":295.266,"temp_max":295.266,"pressure":1025.14,"sea_level":1029.5,"grnd_level":1025.14,"humidity":69,"temp_kf":0},"weather":[{"id":500,"main":"Rain","description":"light rain","icon":"10d"}],"clouds":{"all":92},"wind":{"speed":5.26,"deg":297.501},"rain":{"3h":0.01},"sys":{"pod":"d"},"dt_txt":"2018-08-20 12:00:00"},{"dt":1534777200,"main":{"temp":296.227,"temp_min":296.227,"temp_max":296.227,"pressure":1025.7,"sea_level":1030.18,"grnd_level":1025.7,"humidity":58,"temp_kf":0},"weather":[{"id":800,"main":"Clear","description":"clear sky","icon":"01d"}],"clouds":{"all":0},"wind":{"speed":5.96,"deg":308.002},"rain":{},"sys":{"pod":"d"},"dt_txt":"2018-08-20 15:00:00"},{"dt":1534788000,"main":{"temp":292.907,"temp_min":292.907,"temp_max":292.907,"pressure":1026.86,"sea_level":1031.25,"grnd_level":1026.86,"humidity":52,"temp_kf":0},"weather":[{"id":800,"main":"Clear","description":"clear sky","icon":"01d"}],"clouds":{"all":0},"wind":{"speed":5.02,"deg":314.505},"rain":{},"sys":{"pod":"d"},"dt_txt":"2018-08-20 18:00:00"},{"dt":1534798800,"main":{"temp":288.029,"temp_min":288.029,"temp_max":288.029,"pressure":1028.33,"sea_level":1032.76,"grnd_level":1028.33,"humidity":71,"temp_kf":0},"weather":[{"id":800,"main":"Clear","description":"clear sky","icon":"01n"}],"clouds":{"all":0},"wind":{"speed":3.47,"deg":312.002},"rain":{},"sys":{"pod":"n"},"dt_txt":"2018-08-20 21:00:00"},{"dt":1534809600,"main":{"temp":284.827,"temp_min":284.827,"temp_max":284.827,"pressure":1029.14,"sea_level":1033.67,"grnd_level":1029.14,"humidity":93,"temp_kf":0},"weather":[{"id":800,"main":"Clear","description":"clear sky","icon":"01n"}],"clouds":{"all":0},"wind":{"speed":2.75,"deg":302.504},"rain":{},"sys":{"pod":"n"},"dt_txt":"2018-08-21 00:00:00"},{"dt":1534820400,"main":{"temp":282.478,"temp_min":282.478,"temp_max":282.478,"pressure":1029.53,"sea_level":1034.02,"grnd_level":1029.53,"humidity":88,"temp_kf":0},"weather":[{"id":800,"main":"Clear","description":"clear sky","icon":"01n"}],"clouds":{"all":0},"wind":{"speed":1.26,"deg":284.001},"rain":{},"sys":{"pod":"n"},"dt_txt":"2018-08-21 03:00:00"},{"dt":1534831200,"main":{"temp":286.574,"temp_min":286.574,"temp_max":286.574,"pressure":1030.14,"sea_level":1034.65,"grnd_level":1030.14,"humidity":87,"temp_kf":0},"weather":[{"id":800,"main":"Clear","description":"clear sky","icon":"02d"}],"clouds":{"all":8},"wind":{"speed":1.46,"deg":259},"rain":{},"sys":{"pod":"d"},"dt_txt":"2018-08-21 06:00:00"},{"dt":1534842000,"main":{"temp":291.257,"temp_min":291.257,"temp_max":291.257,"pressure":1030.49,"sea_level":1034.89,"grnd_level":1030.49,"humidity":68,"temp_kf":0},"weather":[{"id":801,"main":"Clouds","description":"few clouds","icon":"02d"}],"clouds":{"all":12},"wind":{"speed":2.06,"deg":298},"rain":{},"sys":{"pod":"d"},"dt_txt":"2018-08-21 09:00:00"},{"dt":1534852800,"main":{"temp":294.679,"temp_min":294.679,"temp_max":294.679,"pressure":1029.32,"sea_level":1033.76,"grnd_level":1029.32,"humidity":57,"temp_kf":0},"weather":[{"id":800,"main":"Clear","description":"clear sky","icon":"01d"}],"clouds":{"all":0},"wind":{"speed":2.08,"deg":275.003},"rain":{},"sys":{"pod":"d"},"dt_txt":"2018-08-21 12:00:00"},{"dt":1534863600,"main":{"temp":296.506,"temp_min":296.506,"temp_max":296.506,"pressure":1027.86,"sea_level":1032.3,"grnd_level":1027.86,"humidity":46,"temp_kf":0},"weather":[{"id":800,"main":"Clear","description":"clear sky","icon":"01d"}],"clouds":{"all":0},"wind":{"speed":2.02,"deg":291.501},"rain":{},"sys":{"pod":"d"},"dt_txt":"2018-08-21 15:00:00"},{"dt":1534874400,"main":{"temp":294.763,"temp_min":294.763,"temp_max":294.763,"pressure":1026.92,"sea_level":1031.41,"grnd_level":1026.92,"humidity":46,"temp_kf":0},"weather":[{"id":800,"main":"Clear","description":"clear sky","icon":"01d"}],"clouds":{"all":0},"wind":{"speed":1.3,"deg":295},"rain":{},"sys":{"pod":"d"},"dt_txt":"2018-08-21 18:00:00"},{"dt":1534885200,"main":{"temp":288.243,"temp_min":288.243,"temp_max":288.243,"pressure":1026.71,"sea_level":1031.3,"grnd_level":1026.71,"humidity":77,"temp_kf":0},"weather":[{"id":800,"main":"Clear","description":"clear sky","icon":"01n"}],"clouds":{"all":0},"wind":{"speed":1.22,"deg":38.5},"rain":{},"sys":{"pod":"n"},"dt_txt":"2018-08-21 21:00:00"},{"dt":1534896000,"main":{"temp":286.277,"temp_min":286.277,"temp_max":286.277,"pressure":1026.36,"sea_level":1030.82,"grnd_level":1026.36,"humidity":76,"temp_kf":0},"weather":[{"id":800,"main":"Clear","description":"clear sky","icon":"01n"}],"clouds":{"all":0},"wind":{"speed":1.46,"deg":122.502},"rain":{},"sys":{"pod":"n"},"dt_txt":"2018-08-22 00:00:00"},{"dt":1534906800,"main":{"temp":285.451,"temp_min":285.451,"temp_max":285.451,"pressure":1025.48,"sea_level":1029.99,"grnd_level":1025.48,"humidity":80,"temp_kf":0},"weather":[{"id":800,"main":"Clear","description":"clear sky","icon":"01n"}],"clouds":{"all":0},"wind":{"speed":1.25,"deg":169},"rain":{},"sys":{"pod":"n"},"dt_txt":"2018-08-22 03:00:00"},{"dt":1534917600,"main":{"temp":290.125,"temp_min":290.125,"temp_max":290.125,"pressure":1025.45,"sea_level":1029.85,"grnd_level":1025.45,"humidity":68,"temp_kf":0},"weather":[{"id":800,"main":"Clear","description":"clear sky","icon":"01d"}],"clouds":{"all":0},"wind":{"speed":1.52,"deg":195.003},"rain":{},"sys":{"pod":"d"},"dt_txt":"2018-08-22 06:00:00"},{"dt":1534928400,"main":{"temp":298.625,"temp_min":298.625,"temp_max":298.625,"pressure":1025.58,"sea_level":1030.05,"grnd_level":1025.58,"humidity":50,"temp_kf":0},"weather":[{"id":800,"main":"Clear","description":"clear sky","icon":"01d"}],"clouds":{"all":0},"wind":{"speed":3.76,"deg":245.505},"rain":{},"sys":{"pod":"d"},"dt_txt":"2018-08-22 09:00:00"},{"dt":1534939200,"main":{"temp":300.055,"temp_min":300.055,"temp_max":300.055,"pressure":1025.14,"sea_level":1029.52,"grnd_level":1025.14,"humidity":50,"temp_kf":0},"weather":[{"id":800,"main":"Clear","description":"clear sky","icon":"01d"}],"clouds":{"all":0},"wind":{"speed":4.97,"deg":261.504},"rain":{},"sys":{"pod":"d"},"dt_txt":"2018-08-22 12:00:00"},{"dt":1534950000,"main":{"temp":300.367,"temp_min":300.367,"temp_max":300.367,"pressure":1024.38,"sea_level":1028.77,"grnd_level":1024.38,"humidity":50,"temp_kf":0},"weather":[{"id":801,"main":"Clouds","description":"few clouds","icon":"02d"}],"clouds":{"all":20},"wind":{"speed":4.21,"deg":281},"rain":{},"sys":{"pod":"d"},"dt_txt":"2018-08-22 15:00:00"},{"dt":1534960800,"main":{"temp":297.965,"temp_min":297.965,"temp_max":297.965,"pressure":1024.64,"sea_level":1028.95,"grnd_level":1024.64,"humidity":58,"temp_kf":0},"weather":[{"id":803,"main":"Clouds","description":"broken clouds","icon":"04d"}],"clouds":{"all":76},"wind":{"speed":3.87,"deg":301.505},"rain":{},"sys":{"pod":"d"},"dt_txt":"2018-08-22 18:00:00"},{"dt":1534971600,"main":{"temp":293.485,"temp_min":293.485,"temp_max":293.485,"pressure":1025.35,"sea_level":1029.67,"grnd_level":1025.35,"humidity":79,"temp_kf":0},"weather":[{"id":802,"main":"Clouds","description":"scattered clouds","icon":"03n"}],"clouds":{"all":36},"wind":{"speed":2.86,"deg":321.001},"rain":{},"sys":{"pod":"n"},"dt_txt":"2018-08-22 21:00:00"},{"dt":1534982400,"main":{"temp":291.858,"temp_min":291.858,"temp_max":291.858,"pressure":1025.24,"sea_level":1029.54,"grnd_level":1025.24,"humidity":84,"temp_kf":0},"weather":[{"id":803,"main":"Clouds","description":"broken clouds","icon":"04n"}],"clouds":{"all":56},"wind":{"speed":2.21,"deg":350.501},"rain":{},"sys":{"pod":"n"},"dt_txt":"2018-08-23 00:00:00"},{"dt":1534993200,"main":{"temp":289.56,"temp_min":289.56,"temp_max":289.56,"pressure":1024.28,"sea_level":1028.77,"grnd_level":1024.28,"humidity":93,"temp_kf":0},"weather":[{"id":800,"main":"Clear","description":"clear sky","icon":"01n"}],"clouds":{"all":0},"wind":{"speed":1.36,"deg":1.50275},"rain":{},"sys":{"pod":"n"},"dt_txt":"2018-08-23 03:00:00"},{"dt":1535004000,"main":{"temp":290.902,"temp_min":290.902,"temp_max":290.902,"pressure":1023.59,"sea_level":1027.99,"grnd_level":1023.59,"humidity":84,"temp_kf":0},"weather":[{"id":800,"main":"Clear","description":"clear sky","icon":"01d"}],"clouds":{"all":0},"wind":{"speed":2.01,"deg":72.0123},"rain":{},"sys":{"pod":"d"},"dt_txt":"2018-08-23 06:00:00"},{"dt":1535014800,"main":{"temp":298.164,"temp_min":298.164,"temp_max":298.164,"pressure":1022.21,"sea_level":1026.56,"grnd_level":1022.21,"humidity":62,"temp_kf":0},"weather":[{"id":800,"main":"Clear","description":"clear sky","icon":"01d"}],"clouds":{"all":0},"wind":{"speed":2.85,"deg":125.5},"rain":{},"sys":{"pod":"d"},"dt_txt":"2018-08-23 09:00:00"},{"dt":1535025600,"main":{"temp":302.563,"temp_min":302.563,"temp_max":302.563,"pressure":1019.49,"sea_level":1023.93,"grnd_level":1019.49,"humidity":47,"temp_kf":0},"weather":[{"id":802,"main":"Clouds","description":"scattered clouds","icon":"03d"}],"clouds":{"all":32},"wind":{"speed":4.11,"deg":184.501},"rain":{},"sys":{"pod":"d"},"dt_txt":"2018-08-23 12:00:00"},{"dt":1535036400,"main":{"temp":303.727,"temp_min":303.727,"temp_max":303.727,"pressure":1016.75,"sea_level":1021.01,"grnd_level":1016.75,"humidity":38,"temp_kf":0},"weather":[{"id":802,"main":"Clouds","description":"scattered clouds","icon":"03d"}],"clouds":{"all":36},"wind":{"speed":4.35,"deg":202.504},"rain":{},"sys":{"pod":"d"},"dt_txt":"2018-08-23 15:00:00"}],"city":{"id":2911298,"name":"Hamburg","coord":{"lat":53.5503,"lon":10.0007},"country":"DE","population":1739117}}
